pyacorn/__init__.py
pyacorn/__main__.py
pyacorn/client.py
pyacorn/tasks.json.j2
pyacorn/templates/launch.json.j2
pyacorn/templates/settings.json.j2
pyacorn/templates/tasks.json.j2
pyacorn-0.0.19.dist-info/LICENSE.txt
pyacorn-0.0.19.dist-info/METADATA
pyacorn-0.0.19.dist-info/WHEEL
pyacorn-0.0.19.dist-info/entry_points.txt
pyacorn-0.0.19.dist-info/top_level.txt
pyacorn-0.0.19.dist-info/RECORD
