Metadata-Version: 2.1
Name: pyacorn
Version: 0.0.19
Summary: The python command-line client for the acorn platform
Home-page: UNKNOWN
License: UNKNOWN
Keywords: python acorn cli
Platform: UNKNOWN
Requires-Python: >=3.5,<4
Requires-Dist: click (<8,>=7.1.1)
Requires-Dist: commentjson
Requires-Dist: jinja2 (<3,>=2.10.3)
Requires-Dist: pyfiglet
Requires-Dist: requests (<3,>=2.22.0)
